setup.py
ezodf2/__init__.py
ezodf2/base.py
ezodf2/body.py
ezodf2/bytestreammanager.py
ezodf2/cells.py
ezodf2/cellspancontroller.py
ezodf2/compatibility.py
ezodf2/conf.py
ezodf2/const.py
ezodf2/content.py
ezodf2/document.py
ezodf2/drawingpage.py
ezodf2/filemanager.py
ezodf2/manifest.py
ezodf2/meta.py
ezodf2/nodeorganizer.py
ezodf2/nodestructurechecker.py
ezodf2/nodestructuretags.py
ezodf2/observer.py
ezodf2/pagecontainer.py
ezodf2/pages.py
ezodf2/presentationpage.py
ezodf2/propertymixins.py
ezodf2/protection.py
ezodf2/sheets.py
ezodf2/styles.py
ezodf2/table.py
ezodf2/tablecolumncontroller.py
ezodf2/tablenormalizer.py
ezodf2/tablerowcontroller.py
ezodf2/tableutils.py
ezodf2/text.py
ezodf2/timeparser.py
ezodf2/whitespaces.py
ezodf2/wrapcache.py
ezodf2/xmlns.py
ezodf2.egg-info/PKG-INFO
ezodf2.egg-info/SOURCES.txt
ezodf2.egg-info/dependency_links.txt
ezodf2.egg-info/requires.txt
ezodf2.egg-info/top_level.txt