Metadata-Version: 1.1
Name: ezodf2
Version: 0.2.9
Summary: A Python package to create/manipulate OpenDocumentFormat files.
Home-page: http://github.com/iwschris/ezodf2
Author: Chris Reynolds
Author-email: chris@britecore.com
License: GPLv3
Keywords: ODF,OpenDocumentFormat,OpenOffice,LibreOffice
Platform: OS Independent
Classifier: Development Status :: 3 - Alpha
Classifier: License :: OSI Approved :: GNU General Public License (GPL)
Classifier: Operating System :: OS Independent
Classifier: Programming Language :: Python :: 2.7
Classifier: Programming Language :: Python :: 3
Classifier: Programming Language :: Python :: 3.2
Classifier: Programming Language :: Python :: 3.3
Classifier: Intended Audience :: Developers
Classifier: Topic :: Software Development :: Libraries :: Python Modules
Classifier: Topic :: Office/Business :: Office Suites
